endf/__init__.py
endf/_records.cp314t-win32.pyd
endf/_records.cpp
endf/ace.py
endf/data.py
endf/fileutils.py
endf/function.py
endf/incident_neutron.py
endf/material.py
endf/mf1.py
endf/mf12.py
endf/mf13.py
endf/mf14.py
endf/mf15.py
endf/mf2.py
endf/mf23.py
endf/mf26.py
endf/mf27.py
endf/mf28.py
endf/mf3.py
endf/mf33.py
endf/mf34.py
endf/mf4.py
endf/mf40.py
endf/mf5.py
endf/mf6.py
endf/mf7.py
endf/mf8.py
endf/mf9.py
endf/product.py
endf/reaction.py
endf/records.py
endf-0.1.9.dist-info/licenses/LICENSE
endf-0.1.9.dist-info/METADATA
endf-0.1.9.dist-info/WHEEL
endf-0.1.9.dist-info/top_level.txt
endf-0.1.9.dist-info/RECORD
